{"commitInfo":{"timestamp":1771231003601,"userId":"1867883896243705","userName":"simon.olofsson@hivestreaming.com","operation":"WRITE","operationParameters":{"mode":"Append","statsOnLoad":false,"partitionBy":"[\"eventDate\"]"},"notebook":{"notebookId":"154994726861542"},"clusterId":"0123-061243-o2ugorea","readVersion":64,"isolationLevel":"WriteSerializable","isBlindAppend":true,"operationMetrics":{"numFiles":"1","numOutputRows":"8","numOutputBytes":"10744"},"tags":{"noRowsCopied":"true","restoresDeletedRows":"false"},"engineInfo":"Databricks-Runtime/15.4.x-cpu-ml-scala2.12","txnId":"b95b9322-c63f-4cff-8174-947bd064370b"}}
{"add":{"path":"eventDate=2025-11-13/part-00000-62764574-f974-4977-b970-351c75ef3b7b.c000.snappy.parquet","partitionValues":{"eventDate":"2025-11-13"},"size":10744,"modificationTime":1771230999000,"dataChange":true,"stats":"{\"numRecords\":8,\"minValues\":{\"customerId\":\"4cb0f1c9-19b3-408c-8a09-03bf1538\",\"contentId\":\"5761d026-0569-437e-9033-16618b2c\",\"clientId\":\"35a1e10d-9cad-4839-b5a3-1e1ba091\",\"timestampInfo\":{\"server\":1763032670256,\"agent\":1763032670242},\"player\":{\"bufferings\":0,\"bufferingTime\":0},\"totalDistribution\":{\"sourceTraffic\":{\"requests\":2,\"responses\":1.0,\"requestedData\":442740,\"receivedData\":442740},\"p2pTraffic\":{\"requests\":0,\"responses\":0.0,\"requestedData\":0,\"receivedData\":0}}},\"maxValues\":{\"customerId\":\"4cb0f1c9-19b3-408c-8a09-03bf1538\",\"contentId\":\"5761d026-0569-437e-9033-16618b2c\",\"clientId\":\"f63c5309-d0c6-4643-b9b0-63306d06\",\"timestampInfo\":{\"server\":1763032678781,\"agent\":1763032679432},\"player\":{\"bufferings\":2,\"bufferingTime\":7578},\"totalDistribution\":{\"sourceTraffic\":{\"requests\":6,\"responses\":4.0,\"requestedData\":13228432,\"receivedData\":13228432},\"p2pTraffic\":{\"requests\":4,\"responses\":4.0,\"requestedData\":4492072,\"receivedData\":4492072}}},\"nullCount\":{\"customerId\":0,\"contentId\":0,\"clientId\":0,\"timestampInfo\":{\"server\":0,\"agent\":0},\"player\":{\"bufferings\":0,\"bufferingTime\":0},\"totalDistribution\":{\"sourceTraffic\":{\"requests\":0,\"responses\":0,\"requestedData\":0,\"receivedData\":0},\"p2pTraffic\":{\"requests\":0,\"responses\":0,\"requestedData\":0,\"receivedData\":0}},\"qualityDistribution\":0},\"tightBounds\":true}","tags":{"INSERTION_TIME":"1771230999000000","MIN_INSERTION_TIME":"1771230999000000","MAX_INSERTION_TIME":"1771230999000000","OPTIMIZE_TARGET_SIZE":"268435456"}}}
